coverlovin2/__init__.py
coverlovin2/__main__.py
coverlovin2/app.py
CoverLovin2-0.7.5.dist-info/LICENSE.TXT
CoverLovin2-0.7.5.dist-info/METADATA
CoverLovin2-0.7.5.dist-info/WHEEL
CoverLovin2-0.7.5.dist-info/entry_points.txt
CoverLovin2-0.7.5.dist-info/top_level.txt
CoverLovin2-0.7.5.dist-info/RECORD
