Metadata-Version: 2.1
Name: CoverLovin2
Version: 0.7.5
Summary: Download music album cover art for a music collection.
Home-page: https://github.com/jtmoon79/coverlovin2
Author: James Thomas Moon
License: Apache License 2.0 (Apache-2.0)
Project-URL: Source, https://github.com/jtmoon79/coverlovin2
Project-URL: Bug Reports, https://github.com/jtmoon79/coverlovin2/issues
Keywords: audio image music
Classifier: Development Status :: 4 - Beta
Classifier: Environment :: Console
Classifier: Operating System :: OS Independent
Classifier: Natural Language :: English
Classifier: License :: OSI Approved :: Apache Software License
Classifier: Programming Language :: Python :: 3.8
Classifier: Programming Language :: Python :: 3.9
Classifier: Programming Language :: Python :: 3.10
Classifier: Programming Language :: Python :: 3.11
Classifier: Programming Language :: Python :: 3.12
Classifier: Programming Language :: Python :: 3 :: Only
Classifier: Topic :: Multimedia :: Sound/Audio
Requires-Python: >=3.8
License-File: LICENSE.TXT
Requires-Dist: attrs ==23.1.0
Requires-Dist: requests ==2.31.0
Requires-Dist: musicbrainzngs ==0.7.1
Requires-Dist: mutagen ==1.47.0
Requires-Dist: Pillow ==10.1.0
Requires-Dist: tabulate ==0.9.0
Requires-Dist: typing-extensions ==4.8.0
Provides-Extra: dev
Requires-Dist: codecov ; extra == 'dev'
Requires-Dist: coveralls ; extra == 'dev'
Requires-Dist: exceptiongroup ; extra == 'dev'
Requires-Dist: mypy ; extra == 'dev'
Requires-Dist: pip-run ; extra == 'dev'
Requires-Dist: pipenv ; extra == 'dev'
Requires-Dist: pluggy ; extra == 'dev'
Requires-Dist: pytest ; extra == 'dev'
Requires-Dist: pytest-cov ; extra == 'dev'
Requires-Dist: pytest-dependency ; extra == 'dev'
Requires-Dist: pyyaml >=4.2b1 ; extra == 'dev'
Requires-Dist: setuptools ; extra == 'dev'
Requires-Dist: twine ; extra == 'dev'
Requires-Dist: types-requests ==2.31.0.10 ; extra == 'dev'
Requires-Dist: types-setuptools ; extra == 'dev'
Requires-Dist: types-tabulate ==0.9.0.3 ; extra == 'dev'
Requires-Dist: wheel ; extra == 'dev'
Requires-Dist: yamllint ; extra == 'dev'
